Metadata-Version: 2.1
Name: dash-wordcloud
Version: 0.3.4
Summary: A Dash UI component for wordcloud visualization
Home-page: UNKNOWN
Author: ssword
Author-email: ssword@gmail.com
License: MIT
Platform: UNKNOWN
